napari_sc3d_viewer/__init__.py
napari_sc3d_viewer/_display_embryo.py
napari_sc3d_viewer/_umap_selection.py
napari_sc3d_viewer/_utils.py
napari_sc3d_viewer/_widget_load.py
napari_sc3d_viewer/_widget_register.py
napari_sc3d_viewer/napari.yaml
napari_sc3d_viewer/_tests/__init__.py
napari_sc3d_viewer/_tests/test_widget.py
napari_sc3d_viewer-2.0.0.dist-info/licenses/LICENSE
napari_sc3d_viewer-2.0.0.dist-info/METADATA
napari_sc3d_viewer-2.0.0.dist-info/WHEEL
napari_sc3d_viewer-2.0.0.dist-info/entry_points.txt
napari_sc3d_viewer-2.0.0.dist-info/top_level.txt
napari_sc3d_viewer-2.0.0.dist-info/RECORD
