Metadata-Version: 2.4
Name: napari-sc3D-viewer
Version: 2.0.0
Summary: A plugin to visualize 3D single cell omics
Home-page: https://github.com/GuignardLab/napari-sc3D-viewer
Author: Leo Guignard
Author-email: leo.guignard@univ-amu.fr
License: MIT
Project-URL: Bug Tracker, https://github.com/GuignardLab/napari-sc3D-viewer/issues
Project-URL: Documentation, https://github.com/GuignardLab/napari-sc3D-viewer#README.md
Project-URL: Source Code, https://github.com/GuignardLab/napari-sc3D-viewer
Project-URL: User Support, https://github.com/GuignardLab/napari-sc3D-viewer/issues
Project-URL: Twitter, https://twitter.com/guignardlab
Classifier: Development Status :: 4 - Beta
Classifier: Intended Audience :: Developers
Classifier: Framework :: napari
Classifier: Topic :: Software Development :: Testing
Classifier: Programming Language :: Python
Classifier: Programming Language :: Python :: 3
Classifier: Programming Language :: Python :: 3.8
Classifier: Programming Language :: Python :: 3.9
Classifier: Programming Language :: Python :: 3.10
Classifier: Operating System :: OS Independent
Classifier: License :: OSI Approved :: MIT License
Requires-Python: >=3.8
License-File: LICENSE
Requires-Dist: numpy
Requires-Dist: magicgui
Requires-Dist: qtpy
Requires-Dist: sc-3D>=2.0
Requires-Dist: matplotlib
Provides-Extra: testing
Requires-Dist: tox; extra == "testing"
Requires-Dist: pytest; extra == "testing"
Requires-Dist: pytest-cov; extra == "testing"
Requires-Dist: pytest-qt; extra == "testing"
Requires-Dist: napari; extra == "testing"
Requires-Dist: pyqt5; extra == "testing"
Provides-Extra: pyvista
Requires-Dist: pyvista; extra == "pyvista"
Dynamic: license-file
